{
  "mobile": {
    "android": [
      "Redmi Note 5 Build/PKQ1.180904.001",
      "MI 6 Build/PKQ1.190118.001",
      "EVR-AL00 Build/HUAWEIEVR-AL00",
      "JKM-AL00b Build/HUAWEIJKM-AL00b",
      "COR-TL10 Build/HUAWEICOR-TL10",
      "VCE-AL00 Build/HUAWEIVCE-AL00",
      "CLT-AL00 Build/HUAWEICLT-AL00",
      "HMA-AL00 Build/HUAWEIHMA-AL00",
      "HWI-AL00 Build/HUAWEIHWI-AL00",
      "SKW-A0 Build/SKYW2001202CN00MQ0",
      "PBAM00 Build/OPM1.171019.026",
      "LIO-AN00 Build/HUAWEILIO-AN00",
      "Redmi Note 5 Build/OPM1.171019.011",
      "ELE-AL00 Build/HUAWEIELE-AL0001",
      "DUB-TL00 Build/HUAWEIDUB-TL00",
      "M1813 Build/O11019",
      "CLT-AL01 Build/HUAWEICLT-AL01",
      "VOG-AL00 Build/HUAWEIVOG-AL00",
      "Mi-4c Build/NRD91M",
      "COL-AL10 Build/HUAWEICOL-AL10",
      "Redmi Note 7 Build/PKQ1.180904.001",
      "HLK-AL10 Build/HONORHLK-AL10",
      "SEA-AL10 Build/HUAWEISEA-AL10",
      "16s Pro Build/PKQ1.190616.001",
      "V1813BT Build/PKQ1.181030.001",
      "OPPO A79k Build/N6F26Q",
      "vivo X9s L Build/OPM1.171019.019",
      "RNE-AL00 Build/HUAWEIRNE-AL00",
      "M2 E Build/MMB29U",
      "MI PLAY Build/O11019",
      "NX606J Build/OPM1.171019.026",
      "OPPO A57 Build/MMB29M",
      "JKM-AL00a Build/HUAWEIJKM-AL00a",
      "JNY-AL10 Build/HUAWEIJNY-AL10",
      "vivo X21 Build/PKQ1.180819.001",
      "MI 9 Build/QKQ1.190825.002",
      "LYA-AL10 Build/HUAWEILYA-AL10",
      "HLK-AL00 Build/HONORHLK-AL00",
      "MI 9 SE Build/PKQ1.181121.001",
      "LON-AL00 Build/HUAWEILON-AL00",
      "YAL-AL00 Build/HUAWEIYAL-AL00",
      "V1913A Build/P00610",
      "CLT-TL01 Build/HUAWEICLT-TL01",
      "SM-G9750 Build/QP1A.190711.020",
      "LIO-AL00 Build/HUAWEILIO-AL00",
      "Redmi 5 Plus Build/N2G47H",
      "ONEPLUS A6000 Build/PKQ1.180716.001",
      "OPPO_A59S Build/KOT49H",
      "ALP-TL00 Build/HUAWEIALP-TL00",
      "ELE-AL00 Build/HUAWEIELE-AL00",
      "PACT00 Build/PPR1.180610.011",
      "Redmi K20 Pro Build/QKQ1.190825.002",
      "HUAWEI NXT-AL10 Build/HUAWEINXT-AL10",
      "STK-AL00 Build/HUAWEISTK-AL00",
      "Redmi 6 Pro Build/PKQ1.180917.001",
      "Redmi 4X Build/N2G47H",
      "M1822 Build/OPM1.171019.026",
      "V1916A Build/PKQ1.190714.001",
      "PBDM00 Build/PKQ1.190519.001",
      "MI 8 Build/PKQ1.180729.001",
      "V1836A Build/PKQ1.181030.001",
      "JSN-AL00a Build/HONORJSN-AL00a",
      "vivo X9s Build/OPM1.171019.019",
      "vivo Y85A Build/OPM1.171019.011",
      "1809-A01 Build/OPM1",
      "SM-A7050 Build/PPR1.180610.011",
      "MI 5X Build/OPM1.171019.019",
      "MI 8 SE Build/QKQ1.190828.002",
      "Redmi 7 Build/PKQ1.181021.001",
      "V1816A Build/PKQ1.180819.001",
      "PIC-AL00 Build/HUAWEIPIC-AL00",
      "SM-C7010 Build/R16NW",
      "Redmi Note 8 Pro Build/QP1A.190711.020",
      "V1732A Build/O11019",
      "ALP-AL00 Build/HUAWEIALP-AL00",
      "PRA-TL10 Build/HONORPRA-TL10",
      "INE-AL00 Build/HUAWEIINE-AL00",
      "BLA-TL00 Build/HUAWEIBLA-TL00",
      "OPPO R11 Build/NMF26X",
      "MIX 2S Build/QKQ1.190828.002",
      "vivo Y71A Build/OPM1.171019.011",
      "BLN-AL40 Build/HONORBLN-AL40",
      "ANE-AL00 Build/HUAWEIANE-AL00",
      "Android 7.1.1",
      "rv:68.0",
      "OPPO R9sk Build/NMF26F",
      "MB200 Build/GRJ22",
      "Nexus One Build/FRF91",
      "Android 10",
      "SM-S931B Build/AP3A.240905.015.A2",
      "SM-S931U Build/AP3A.240905.015.A2",
      "SM-F9560 Build/UP1A.231005.007",
      "Android 14",
      "SM-G556B/DS",
      "rv:130.0",
      "Android 13",
      "Android 12",
      "Pixel 9 Pro Build/AD1A.240418.003",
      "Pixel 9 Build/AD1A.240411.003.A5",
      "Pixel 8 Pro Build/AP4A.250105.002",
      "Pixel 8 Build/AP4A.250105.002",
      "Pixel 7 Pro",
      "Pixel 6 Pro",
      "moto g - 2025 Build/V1VK35.22-13-2",
      "moto g power 5G - 2024 Build/U1UD34.16-62",
      "motorola razr 50 ultra Build/U3UX34.56-29-2",
      "moto g pure",
      "moto g stylus 5G",
      "23129RAA4G Build/TKQ1.221114.001",
      "24129RT7CC Build/AP3A.240905.015.A2",
      "HBP-LX9 Build/HUAWEIHBP-L29",
      "ADA-AL00 Build/HUAWEIADA-AL00",
      "PSD-AL00 Build/HUAWEIPSD-AL00",
      "24030PN60G Build/UKQ1.231003.002",
      "2405CPX3DC Build/UKQ1.240116.001",
      "Redmi Note 9 Pro",
      "Redmi Note 8 Pro",
      "M2102J20SG",
      "LG-V410/V41020c Build/LRX22G"
    ],
    "ios": [
      "CPU iPhone OS 13_0 like Mac OS X",
      "CPU iPhone OS 12_4_5 like Mac OS X",
      "CPU iPhone OS 11_4_1 like Mac OS X",
      "CPU iPhone OS 11_2_6 like Mac OS X",
      "CPU iPhone OS 3_0 like Mac OS X",
      "CPU iPhone OS 4_0 like Mac OS X",
      "CPU iPhone OS 18_3_2 like Mac OS X",
      "CPU iPhone OS 18_2_1 like Mac OS X",
      "CPU iPhone OS 18_3_1 like Mac OS X",
      "CPU iPhone OS 17_5_1 like Mac OS X",
      "CPU iPhone OS 15_6_1 like Mac OS X",
      "CPU iPhone OS 15_4 like Mac OS X",
      "CPU iPhone OS 15_0 like Mac OS X",
      "CPU iPhone OS 14_0 like Mac OS X",
      "CPU iPhone OS 12_0 like Mac OS X",
      "CPU iPhone OS 11_0 like Mac OS X",
      "CPU iPhone OS 10_0_1 like Mac OS X"
    ]
  },
  "desktop": {
    "windows": [
      "Win64",
      "WOW64"
    ],
    "macos": [
      "CPU OS 18_3_2 like Mac OS X",
      "Intel Mac OS X 10_15_7",
      "Intel Mac OS X 10_15_3",
      "Intel Mac OS X 10_10_5",
      "Intel Mac OS X 10_12_6",
      "PPC Mac OS X"
    ]
  },
  "tablet": {
    "ios": [
      "CPU OS 3_2 like Mac OS X"
    ],
    "android": [
      "Xoom Build/HRI39",
      "SM-X906C Build/QP1A.190711.020",
      "Lenovo YT-J706X",
      "Pixel C Build/NRD90M",
      "SGP771 Build/32.2.A.0.253",
      "SHIELD Tablet K1 Build/MRA58K",
      "SM-T827R4 Build/NRD90M",
      "SAMSUNG SM-T550 Build/LRX22G",
      "KFTHWI Build/KTU84M",
      "DOOM PRO 5G Build/PPR1.180610.011",
      "NEO-X5-116A Build/JDQ39"
    ]

  }
}
